zWell_model/__init__.py
zWell_model/allModel.py
zWell_model/utils.py
zWell_model/convNet/ConvNetV1.py
zWell_model/convNet/ConvNetV2.py
zWell_model/convNet/__init__.py
zWell_model/convNet/convNetWork.py
zWell_model/denseNet/DenseNet.py
zWell_model/denseNet/DenseNetV1.py
zWell_model/denseNet/__init__.py
zWell_model/denseNet/utils.py
zWell_model/resNet/ResNetV1.py
zWell_model/resNet/__init__.py
zWell_model/resNet/resNetWork.py
zWell_model/resNet/utils.py
zWell_model-0.0.2.20230528.dist-info/LICENSE
zWell_model-0.0.2.20230528.dist-info/METADATA
zWell_model-0.0.2.20230528.dist-info/WHEEL
zWell_model-0.0.2.20230528.dist-info/top_level.txt
zWell_model-0.0.2.20230528.dist-info/RECORD
