Metadata-Version: 2.1
Name: zWell-model
Version: 0.0.2.20230528
Summary: Deep learning model adapter, used to quickly create various deep learning models.
Author-email: BeardedManZhao <liming7887@qq.com>
Project-URL: Homepage, https://github.com/BeardedManZhao/ZWell-model.git
Project-URL: Bug Tracker, https://github.com/BeardedManZhao/ZWell-model/issues
Classifier: Programming Language :: Python :: 3
Classifier: License :: OSI Approved :: Apache Software License
Classifier: Operating System :: OS Independent
Requires-Python: >=3.6
License-File: LICENSE
